{
  "songs": [
    {
      "title": "Without Me",
      "artist": "Halsey",
      "album": "Manic",
      "year": 2019,
      "genre": "Pop",
      "duration": "3:21",
      "artwork": "album-arts/without-me.jpg",
      "url": "music-data/Without Me.mp3",
      "id": "1",
      "lyrics": "Found you when your heart was broke..."
    },
    {
      "id": 1696271777890,
      "title": "Chop Suey",
      "artist": "System Of A Down",
      "album": "Toxicity",
      "year": "2001",
      "genre": "Nu metal",
      "duration": "3:29",
      "artwork": "album-arts/chop-suey.jpg",
      "url": "music-data/Chop Suey.m4a",
      "lyrics": "Wake up (wake up) Grab a brush and put a little make-up..."
    }
  ]
}